RndTextGen/__init__.py
RndTextGen/rus_rnd_text.py
RndTextGen-0.0.1.dist-info/METADATA
RndTextGen-0.0.1.dist-info/WHEEL
RndTextGen-0.0.1.dist-info/top_level.txt
RndTextGen-0.0.1.dist-info/RECORD
