Metadata-Version: 2.1
Name: RndTextGen
Version: 0.0.1
Summary: This is a python library for generating random text.
Home-page: https://github.com/LincolnCox29/Random-Text-Generator
Author: Lincoln Cox (Dmitry Vakhnenko)
Author-email: just.kcgo@gmail.com
Project-URL: GitHub, https://github.com/LincolnCox29
Keywords: Random Text
Classifier: Programming Language :: Python :: 3.11
Classifier: Operating System :: OS Independent
Requires-Python: >=3.11
